[
  {
    "LayerId": 240066,
    "Name": "env_location",
    "_InstanceObjects": 52,
    "InstanceObjectCount": 2,
    "ToolModeVisible": 1,
    "ToolModeReadOnly": 0,
    "IsBushLayer": 0,
    "PS3Visible": 1,
    "_LayerSetReferencedList": 208,
    "FestivalID": 0,
    "FestivalPhaseID": 0,
    "IsTemporary": 0,
    "IsHousing": 0,
    "VersionMask": 0,
    "ObSetReferencedList": 220,
    "ObSetReferencedListCount": 0,
    "ObSetEnableReferencedList": 220,
    "ObSetEnableReferencedListCount": 0,
    "LayerSetReferencedList": {
      "ReferencedType": 0,
      "LayerSets": 12,
      "LayerSetCount": 0
    },
    "InstanceObjects": [
      {
        "AssetType": 47,
        "InstanceId": 7881013,
        "Name": "",
        "Transform": {
          "Translation": {
            "x": 100.0,
            "y": -1000.0,
            "z": 100.0
          },
          "Rotation": {
            "x": 0.0,
            "y": -0.0,
            "z": 0.0
          },
          "Scale": {
            "x": 1.0,
            "y": 1.0,
            "z": 1.0
          }
        },
        "Object": {
          "SHAmbientLightAssetPath": "bg/ex3/01_nvt_n4/goe/n4g1/level/envl/evl7881013.amb",
          "EnvMapAssetPath": "bg/ex3/01_nvt_n4/goe/n4g1/level/envl/evl7881013.tex"
        }
      },
      {
        "AssetType": 1,
        "InstanceId": 8035828,
        "Name": "",
        "Transform": {
          "Translation": {
            "x": 100.0,
            "y": -1000.0,
            "z": 100.0
          },
          "Rotation": {
            "x": 0.0,
            "y": 0.0,
            "z": 0.0
          },
          "Scale": {
            "x": 1.0,
            "y": 1.0,
            "z": 1.0
          }
        },
        "Object": {
          "AssetPath": "bg/ex3/01_nvt_n4/goe/n4g1/bgparts/n4g1_a0_shk01.mdl",
          "CollisionAssetPath": "",
          "CollisionType": 0,
          "AttributeMask": 0,
          "Attribute": 28672,
          "CollisionConfig": 0,
          "IsVisible": 0,
          "RenderShadowEnabled": 0,
          "RenderLightShadowEnabled": 0,
          "Padding00": 0,
          "RenderModelClipRange": 0.0
        }
      }
    ],
    "LayerSetReferences": [],
    "OBSetReferencedList": [],
    "OBSetEnableReferencedList": []
  },
  {
    "LayerId": 242869,
    "Name": "gmc01",
    "_InstanceObjects": 52,
    "InstanceObjectCount": 5,
    "ToolModeVisible": 1,
    "ToolModeReadOnly": 0,
    "IsBushLayer": 0,
    "PS3Visible": 1,
    "_LayerSetReferencedList": 832,
    "FestivalID": 0,
    "FestivalPhaseID": 0,
    "IsTemporary": 0,
    "IsHousing": 0,
    "VersionMask": 0,
    "ObSetReferencedList": 844,
    "ObSetReferencedListCount": 0,
    "ObSetEnableReferencedList": 844,
    "ObSetEnableReferencedListCount": 0,
    "LayerSetReferencedList": {
      "ReferencedType": 0,
      "LayerSets": 12,
      "LayerSetCount": 0
    },
    "InstanceObjects": [
      {
        "AssetType": 6,
        "InstanceId": 7920817,
        "Name": "",
        "Transform": {
          "Translation": {
            "x": 100.0,
            "y": 0.0,
            "z": 100.0
          },
          "Rotation": {
            "x": 0.0,
            "y": 0.0,
            "z": 0.0
          },
          "Scale": {
            "x": 1.0,
            "y": 1.0,
            "z": 1.0
          }
        },
        "Object": {
          "AssetPath": "bg/ex3/01_nvt_n4/shared/for_bg/sgbg_n4g1_a1_gmc01.sgb",
          "InitialDoorState": 1,
          "OverriddenMembers": 92,
          "OverriddenMembersCount": 0,
          "InitialRotationState": 1,
          "RandomTimelineAutoPlay": 1,
          "RandomTimelineLoopPlayback": 1,
          "IsCollisionControllableWithoutEObj": 0,
          "BoundCLientPathInstanceId": 0,
          "_MovePathSettings": 92,
          "NotCreateNavimeshDoor": 0,
          "InitialTransformState": 0,
          "InitialColorState": 0,
          "SGOverriddenMembers": null,
          "MovePathSettings": {
            "Mode": 0,
            "AutoPlay": 0,
            "Padding00": 0,
            "Time": 30,
            "Loop": 0,
            "Reverse": 0,
            "Rotation": 0,
            "AccelerateTime": 0,
            "DecelerateTime": 0,
            "VerticalSwingRange": [
              0.0,
              0.0
            ],
            "HorizontalSwingRange": [
              0.0,
              0.0
            ],
            "SwingMoveSpeedRange": [
              30.0,
              30.0
            ],
            "SwingRotation": [
              0.0,
              0.0
            ],
            "SwingRotationSpeedRange": [
              30.0,
              30.0
            ]
          }
        }
      },
      {
        "AssetType": 6,
        "InstanceId": 7923948,
        "Name": "",
        "Transform": {
          "Translation": {
            "x": 100.0,
            "y": 0.0,
            "z": 100.0
          },
          "Rotation": {
            "x": 0.0,
            "y": -0.0,
            "z": 0.0
          },
          "Scale": {
            "x": 1.0,
            "y": 1.0,
            "z": 1.0
          }
        },
        "Object": {
          "AssetPath": "bg/ex3/01_nvt_n4/shared/for_bg/sgbg_n4g1_a1_gmc02.sgb",
          "InitialDoorState": 1,
          "OverriddenMembers": 92,
          "OverriddenMembersCount": 0,
          "InitialRotationState": 1,
          "RandomTimelineAutoPlay": 1,
          "RandomTimelineLoopPlayback": 1,
          "IsCollisionControllableWithoutEObj": 0,
          "BoundCLientPathInstanceId": 0,
          "_MovePathSettings": 92,
          "NotCreateNavimeshDoor": 0,
          "InitialTransformState": 0,
          "InitialColorState": 0,
          "SGOverriddenMembers": null,
          "MovePathSettings": {
            "Mode": 0,
            "AutoPlay": 0,
            "Padding00": 0,
            "Time": 30,
            "Loop": 0,
            "Reverse": 0,
            "Rotation": 0,
            "AccelerateTime": 0,
            "DecelerateTime": 0,
            "VerticalSwingRange": [
              0.0,
              0.0
            ],
            "HorizontalSwingRange": [
              0.0,
              0.0
            ],
            "SwingMoveSpeedRange": [
              30.0,
              30.0
            ],
            "SwingRotation": [
              0.0,
              0.0
            ],
            "SwingRotationSpeedRange": [
              30.0,
              30.0
            ]
          }
        }
      },
      {
        "AssetType": 6,
        "InstanceId": 7919517,
        "Name": "",
        "Transform": {
          "Translation": {
            "x": 0.0,
            "y": 0.0,
            "z": 0.0
          },
          "Rotation": {
            "x": 0.0,
            "y": -0.0,
            "z": 0.0
          },
          "Scale": {
            "x": 1.0,
            "y": 1.0,
            "z": 1.0
          }
        },
        "Object": {
          "AssetPath": "bg/ex3/01_nvt_n4/shared/for_bg/sgbg_n4g1_a1_gmc04.sgb",
          "InitialDoorState": 1,
          "OverriddenMembers": 92,
          "OverriddenMembersCount": 0,
          "InitialRotationState": 1,
          "RandomTimelineAutoPlay": 1,
          "RandomTimelineLoopPlayback": 1,
          "IsCollisionControllableWithoutEObj": 0,
          "BoundCLientPathInstanceId": 0,
          "_MovePathSettings": 92,
          "NotCreateNavimeshDoor": 0,
          "InitialTransformState": 0,
          "InitialColorState": 0,
          "SGOverriddenMembers": null,
          "MovePathSettings": {
            "Mode": 0,
            "AutoPlay": 0,
            "Padding00": 0,
            "Time": 30,
            "Loop": 0,
            "Reverse": 0,
            "Rotation": 0,
            "AccelerateTime": 0,
            "DecelerateTime": 0,
            "VerticalSwingRange": [
              0.0,
              0.0
            ],
            "HorizontalSwingRange": [
              0.0,
              0.0
            ],
            "SwingMoveSpeedRange": [
              30.0,
              30.0
            ],
            "SwingRotation": [
              0.0,
              0.0
            ],
            "SwingRotationSpeedRange": [
              30.0,
              30.0
            ]
          }
        }
      },
      {
        "AssetType": 6,
        "InstanceId": 7921141,
        "Name": "",
        "Transform": {
          "Translation": {
            "x": 0.0,
            "y": 0.0,
            "z": 0.0
          },
          "Rotation": {
            "x": 0.0,
            "y": 3.1415927,
            "z": 0.0
          },
          "Scale": {
            "x": 1.0,
            "y": 1.0,
            "z": 1.0
          }
        },
        "Object": {
          "AssetPath": "bg/ex3/01_nvt_n4/shared/for_bg/sgbg_n4g1_a1_gmc06.sgb",
          "InitialDoorState": 1,
          "OverriddenMembers": 92,
          "OverriddenMembersCount": 0,
          "InitialRotationState": 1,
          "RandomTimelineAutoPlay": 1,
          "RandomTimelineLoopPlayback": 1,
          "IsCollisionControllableWithoutEObj": 0,
          "BoundCLientPathInstanceId": 0,
          "_MovePathSettings": 92,
          "NotCreateNavimeshDoor": 0,
          "InitialTransformState": 0,
          "InitialColorState": 0,
          "SGOverriddenMembers": null,
          "MovePathSettings": {
            "Mode": 0,
            "AutoPlay": 0,
            "Padding00": 0,
            "Time": 30,
            "Loop": 0,
            "Reverse": 0,
            "Rotation": 0,
            "AccelerateTime": 0,
            "DecelerateTime": 0,
            "VerticalSwingRange": [
              0.0,
              0.0
            ],
            "HorizontalSwingRange": [
              0.0,
              0.0
            ],
            "SwingMoveSpeedRange": [
              30.0,
              30.0
            ],
            "SwingRotation": [
              0.0,
              0.0
            ],
            "SwingRotationSpeedRange": [
              30.0,
              30.0
            ]
          }
        }
      },
      {
        "AssetType": 6,
        "InstanceId": 8009831,
        "Name": "",
        "Transform": {
          "Translation": {
            "x": 100.0,
            "y": 1.0,
            "z": 100.0
          },
          "Rotation": {
            "x": 0.0,
            "y": 0.0,
            "z": 0.0
          },
          "Scale": {
            "x": 1.0,
            "y": 1.0,
            "z": 1.0
          }
        },
        "Object": {
          "AssetPath": "bg/ex3/01_nvt_n4/shared/for_bg/sgbg_n4g1_a1_gmc10.sgb",
          "InitialDoorState": 1,
          "OverriddenMembers": 92,
          "OverriddenMembersCount": 0,
          "InitialRotationState": 1,
          "RandomTimelineAutoPlay": 1,
          "RandomTimelineLoopPlayback": 1,
          "IsCollisionControllableWithoutEObj": 0,
          "BoundCLientPathInstanceId": 0,
          "_MovePathSettings": 92,
          "NotCreateNavimeshDoor": 0,
          "InitialTransformState": 0,
          "InitialColorState": 0,
          "SGOverriddenMembers": null,
          "MovePathSettings": {
            "Mode": 0,
            "AutoPlay": 0,
            "Padding00": 0,
            "Time": 30,
            "Loop": 0,
            "Reverse": 0,
            "Rotation": 0,
            "AccelerateTime": 0,
            "DecelerateTime": 0,
            "VerticalSwingRange": [
              0.0,
              0.0
            ],
            "HorizontalSwingRange": [
              0.0,
              0.0
            ],
            "SwingMoveSpeedRange": [
              30.0,
              30.0
            ],
            "SwingRotation": [
              0.0,
              0.0
            ],
            "SwingRotationSpeedRange": [
              30.0,
              30.0
            ]
          }
        }
      }
    ],
    "LayerSetReferences": [],
    "OBSetReferencedList": [],
    "OBSetEnableReferencedList": []
  },
  {
    "LayerId": 240068,
    "Name": "Position_Marker",
    "_InstanceObjects": 52,
    "InstanceObjectCount": 0,
    "ToolModeVisible": 1,
    "ToolModeReadOnly": 0,
    "IsBushLayer": 0,
    "PS3Visible": 1,
    "_LayerSetReferencedList": 52,
    "FestivalID": 0,
    "FestivalPhaseID": 0,
    "IsTemporary": 0,
    "IsHousing": 0,
    "VersionMask": 0,
    "ObSetReferencedList": 64,
    "ObSetReferencedListCount": 0,
    "ObSetEnableReferencedList": 64,
    "ObSetEnableReferencedListCount": 0,
    "LayerSetReferencedList": {
      "ReferencedType": 0,
      "LayerSets": 12,
      "LayerSetCount": 0
    },
    "InstanceObjects": [],
    "LayerSetReferences": [],
    "OBSetReferencedList": [],
    "OBSetEnableReferencedList": []
  }
]